moveread/labels/__init__.py
moveread/labels/__init__.pyi
moveread/labels/annotations.py
moveread/labels/export_.py
moveread_labels-0.1.4.dist-info/METADATA
moveread_labels-0.1.4.dist-info/WHEEL
moveread_labels-0.1.4.dist-info/top_level.txt
moveread_labels-0.1.4.dist-info/RECORD
