Metadata-Version: 2.1
Name: moveread-labels
Version: 0.1.4
Summary: Annotating and exporting labels
Author-email: Marcel Claramunt <marcel@moveread.com>
Project-URL: repo, https://github.com/moveread/python-core
Requires-Python: >=3.10
Requires-Dist: chess-notation
Requires-Dist: chess-utils
Requires-Dist: chess
Requires-Dist: pydantic
Requires-Dist: haskellian
Requires-Dist: lazy-loader
